{
	"info": {
		"_postman_id": "884eab5a-3d56-4b33-801a-aa67c7095c46",
		"name": "Login an Author",
		"schema": "https://schema.getpostman.com/json/collection/v2.1.0/collection.json",
		"_exporter_id": "32218688"
	},
	"item": [
		{
			"name": "New Request",
			"request": {
				"method": "POST",
				"header": [],
				"body": {
					"mode": "raw",
					"raw": "{\r\n   \r\n    \"password\":\"Tushar10$\",\r\n    \"email\":\"tushar@gmail.com\"\r\n}",
					"options": {
						"raw": {
							"language": "json"
						}
					}
				},
				"url": {
					"raw": "http://localhost:3001/auth/login",
					"protocol": "http",
					"host": [
						"localhost"
					],
					"port": "3001",
					"path": [
						"auth",
						"login"
					]
				}
			},
			"response": []
		}
	]
}